gcol/__init__.py
gcol/edge_coloring.py
gcol/face_coloring.py
gcol/node_coloring.py
gcol/output.py
tests/__init__.py
tests/test_gcol.py
gcol-2.1.dist-info/LICENSE
gcol-2.1.dist-info/METADATA
gcol-2.1.dist-info/WHEEL
gcol-2.1.dist-info/top_level.txt
gcol-2.1.dist-info/RECORD
